Metadata-Version: 2.1
Name: temperaturePy
Version: 1.0.0
Summary: Simple Temperature conversion library
Home-page: https://github.com/Harry-Lees/TemperaturePy
Author: Harry Lees
Author-email: harry.lees@gmail.com
License: MIT
Platform: UNKNOWN
Classifier: License :: OSI Approved :: MIT License
Classifier: Programming Language :: Python :: 3
